easya2a/__init__.py
easya2a/cli.py
easya2a/py.typed
easya2a/setup.py
easya2a/config/__init__.py
easya2a/config/agent_config.py
easya2a/config/settings.py
easya2a/core/__init__.py
easya2a/core/agent_wrapper.py
easya2a/core/decorators.py
easya2a/core/executor.py
easya2a/core/server.py
easya2a/core/wrapper.py
easya2a/utils/__init__.py
easya2a/utils/message.py
easya2a/utils/validation.py
easya2a-0.2.dist-info/licenses/LICENSE
easya2a-0.2.dist-info/METADATA
easya2a-0.2.dist-info/WHEEL
easya2a-0.2.dist-info/entry_points.txt
easya2a-0.2.dist-info/top_level.txt
easya2a-0.2.dist-info/RECORD
