Metadata-Version: 2.4
Name: easya2a
Version: 0.2
Summary: 🚀 快速将任何Agent包装为A2A协议服务 - 三步式API设计，一行代码启动
Author-email: whillhill <ooooofish@126.com>
Maintainer-email: whillhill <ooooofish@126.com>
License: MIT
Project-URL: Homepage, https://github.com/whillhill/easya2a
Project-URL: Documentation, https://github.com/whillhill/easya2a#readme
Project-URL: Repository, https://github.com/whillhill/easya2a.git
Project-URL: Bug Tracker, https://github.com/whillhill/easya2a/issues
Project-URL: Changelog, https://github.com/whillhill/easya2a/releases
Project-URL: Source Code, https://github.com/whillhill/easya2a
Keywords: a2a,agent,langchain,ai,wrapper,chatbot,assistant,api,microservice,openai,llm,nlp,automation
Classifier: Development Status :: 5 - Production/Stable
Classifier: Intended Audience :: Developers
Classifier: Intended Audience :: Science/Research
Classifier: License :: OSI Approved :: MIT License
Classifier: Operating System :: OS Independent
Classifier: Programming Language :: Python :: 3
Classifier: Programming Language :: Python :: 3.8
Classifier: Programming Language :: Python :: 3.9
Classifier: Programming Language :: Python :: 3.10
Classifier: Programming Language :: Python :: 3.11
Classifier: Programming Language :: Python :: 3.12
Classifier: Topic :: Software Development :: Libraries :: Python Modules
Classifier: Topic :: Scientific/Engineering :: Artificial Intelligence
Classifier: Topic :: Internet :: WWW/HTTP :: HTTP Servers
Classifier: Topic :: Communications :: Chat
Classifier: Framework :: AsyncIO
Classifier: Framework :: FastAPI
Requires-Python: >=3.8
License-File: LICENSE
Requires-Dist: a2a-sdk>=0.3.0
Requires-Dist: langchain>=0.1.0
Requires-Dist: langchain-core>=0.1.0
Requires-Dist: uvicorn[standard]>=0.20.0
Requires-Dist: starlette>=0.20.0
Requires-Dist: pydantic>=2.0.0
Requires-Dist: typing-extensions>=4.0.0
Requires-Dist: python-dotenv>=1.0.0
Provides-Extra: dev
Requires-Dist: pytest>=7.0.0; extra == "dev"
Requires-Dist: pytest-asyncio>=0.21.0; extra == "dev"
Requires-Dist: pytest-cov>=4.0.0; extra == "dev"
Requires-Dist: black>=23.0.0; extra == "dev"
Requires-Dist: isort>=5.12.0; extra == "dev"
Requires-Dist: flake8>=6.0.0; extra == "dev"
Requires-Dist: mypy>=1.0.0; extra == "dev"
Requires-Dist: pre-commit>=3.0.0; extra == "dev"
Provides-Extra: langchain
Requires-Dist: langchain-openai>=0.1.0; extra == "langchain"
Requires-Dist: langchain-anthropic>=0.1.0; extra == "langchain"
Requires-Dist: langchain-google-genai>=0.1.0; extra == "langchain"
Provides-Extra: full
Requires-Dist: easya2a[langchain]; extra == "full"
Requires-Dist: fastapi>=0.100.0; extra == "full"
Requires-Dist: httpx>=0.24.0; extra == "full"
Requires-Dist: aiofiles>=23.0.0; extra == "full"
Provides-Extra: examples
Requires-Dist: easya2a[full]; extra == "examples"
Requires-Dist: jupyter>=1.0.0; extra == "examples"
Requires-Dist: notebook>=6.0.0; extra == "examples"
Requires-Dist: mcpstore>=0.1.0; extra == "examples"
Dynamic: license-file
